rtl/async_fifo.v
// async_fifo.v -- Parameterized dual-clock (asynchronous) FIFO.
//
// Same external contract as sync_fifo.v, but wr_clk/wr_rst_n and
// rd_clk/rd_rst_n are independent, unrelated clock domains -- this is
// the standard Cummings-style design (Clifford E. Cummings, "Simulation
// and Synthesis Techniques for Asynchronous FIFO Design", SNUG 2002),
// the canonical reference for this exact structure.
//
// Why this is harder than sync_fifo.v: a binary pointer can have
// multiple bits change in the same transition (e.g. 0111 -> 1000, four
// bits flip at once). Synchronizing a multi-bit binary value across a
// clock domain gives no guarantee all bits land in the same cycle on
// the far side -- a partially-updated ("torn") value can be read as a
// completely different, wrong number. Gray code fixes this structurally:
// exactly one bit changes per increment, so a synchronizer sampling a
// Gray-coded pointer mid-transition reads either the old value or the
// new value, never a value that was never valid.
//
// IEEE 1364-2005 only (no SystemVerilog constructs) -- compiled with
// `-g2005` in the Makefile, same as sync_fifo.v.

module async_fifo #(
    parameter DATA_WIDTH = 8,
    parameter DEPTH      = 16   // must be a power of 2
) (
    // Write domain
    input  wire                  wr_clk,
    input  wire                  wr_rst_n,   // active-low, synchronous to wr_clk
    input  wire                  wr_en,
    input  wire [DATA_WIDTH-1:0] wr_data,
    output reg                   full,

    // Read domain
    input  wire                  rd_clk,
    input  wire                  rd_rst_n,   // active-low, synchronous to rd_clk
    input  wire                  rd_en,
    output reg  [DATA_WIDTH-1:0] rd_data,
    output reg                   empty
);

    localparam ADDR_WIDTH = $clog2(DEPTH);

    reg [DATA_WIDTH-1:0] mem [0:DEPTH-1];

    // All pointer/synchronizer registers declared up front: the write
    // domain's synchronizer references the read domain's rd_ptr_gray
    // (and vice versa), so under strict IEEE 1364-2005 elaboration
    // (-g2005) every signal must be declared before any use, regardless
    // of which "domain section" below it conceptually belongs to.
    reg [ADDR_WIDTH:0] wr_ptr_bin, wr_ptr_gray;
    reg [ADDR_WIDTH:0] rd_ptr_bin, rd_ptr_gray;
    reg [ADDR_WIDTH:0] rd_ptr_gray_sync1, rd_ptr_gray_sync2;
    reg [ADDR_WIDTH:0] wr_ptr_gray_sync1, wr_ptr_gray_sync2;

    // -----------------------------------------------------------------
    // Write domain: binary pointer (for memory addressing) + its Gray
    // -coded twin (the only thing that ever crosses into the read
    // domain).
    // -----------------------------------------------------------------
    wire [ADDR_WIDTH:0] wr_ptr_bin_next  = wr_ptr_bin + (wr_en && !full);
    wire [ADDR_WIDTH:0] wr_ptr_gray_next = (wr_ptr_bin_next >> 1) ^ wr_ptr_bin_next;

    always @(posedge wr_clk) begin
        if (!wr_rst_n) begin
            wr_ptr_bin  <= {(ADDR_WIDTH+1){1'b0}};
            wr_ptr_gray <= {(ADDR_WIDTH+1){1'b0}};
        end else begin
            wr_ptr_bin  <= wr_ptr_bin_next;
            wr_ptr_gray <= wr_ptr_gray_next;
            if (wr_en && !full)
                mem[wr_ptr_bin[ADDR_WIDTH-1:0]] <= wr_data;
        end
    end

    // 2-flop synchronizer bringing the read pointer's Gray code into
    // the write domain. Two stages, not one: the first flop is the one
    // that could theoretically go metastable catching an
    // asynchronously-changing input; the second flop gives it a full
    // clock period to resolve before anything downstream uses the
    // value. (Functional RTL simulation can't actually model that
    // metastable resolution -- see README's CDC section for exactly
    // what this testbench can and can't prove.)
    always @(posedge wr_clk) begin
        if (!wr_rst_n) begin
            rd_ptr_gray_sync1 <= {(ADDR_WIDTH+1){1'b0}};
            rd_ptr_gray_sync2 <= {(ADDR_WIDTH+1){1'b0}};
        end else begin
            rd_ptr_gray_sync1 <= rd_ptr_gray;
            rd_ptr_gray_sync2 <= rd_ptr_gray_sync1;
        end
    end

    // Full when the *next* write Gray pointer would equal the
    // synchronized read Gray pointer with its top two bits inverted --
    // the Gray-code equivalent of "write pointer has lapped read
    // pointer by exactly one full trip around the buffer." Registered
    // (not a bare combinational assign) so `full` never glitches
    // mid-comparison.
    wire full_next = (wr_ptr_gray_next ==
        {~rd_ptr_gray_sync2[ADDR_WIDTH:ADDR_WIDTH-1], rd_ptr_gray_sync2[ADDR_WIDTH-2:0]});

    always @(posedge wr_clk) begin
        if (!wr_rst_n)
            full <= 1'b0;
        else
            full <= full_next;
    end

    // -----------------------------------------------------------------
    // Read domain: mirror image of the write domain.
    // -----------------------------------------------------------------
    wire [ADDR_WIDTH:0] rd_ptr_bin_next  = rd_ptr_bin + (rd_en && !empty);
    wire [ADDR_WIDTH:0] rd_ptr_gray_next = (rd_ptr_bin_next >> 1) ^ rd_ptr_bin_next;

    always @(posedge rd_clk) begin
        if (!rd_rst_n) begin
            rd_ptr_bin  <= {(ADDR_WIDTH+1){1'b0}};
            rd_ptr_gray <= {(ADDR_WIDTH+1){1'b0}};
            rd_data     <= {DATA_WIDTH{1'b0}};
        end else begin
            rd_ptr_bin  <= rd_ptr_bin_next;
            rd_ptr_gray <= rd_ptr_gray_next;
            if (rd_en && !empty)
                rd_data <= mem[rd_ptr_bin[ADDR_WIDTH-1:0]];
        end
    end

    // 2-flop synchronizer bringing the write pointer's Gray code into
    // the read domain.
    always @(posedge rd_clk) begin
        if (!rd_rst_n) begin
            wr_ptr_gray_sync1 <= {(ADDR_WIDTH+1){1'b0}};
            wr_ptr_gray_sync2 <= {(ADDR_WIDTH+1){1'b0}};
        end else begin
            wr_ptr_gray_sync1 <= wr_ptr_gray;
            wr_ptr_gray_sync2 <= wr_ptr_gray_sync1;
        end
    end

    // Empty when the *next* read Gray pointer would equal the
    // synchronized write Gray pointer exactly -- no bit inversion
    // needed here, unlike full: pointers being Gray-equal always means
    // "caught up," whether that's because nothing was ever written or
    // because everything written has been read.
    wire empty_next = (rd_ptr_gray_next == wr_ptr_gray_sync2);

    always @(posedge rd_clk) begin
        if (!rd_rst_n)
            empty <= 1'b1;
        else
            empty <= empty_next;
    end

endmodule

results/waves_async.vcd
$date
	Sat Sep 12 23:48:36 2026
$end
$version
	Icarus Verilog
$end
$timescale
	1ps
$end
$scope module async_fifo $end
$var wire 1 ! rd_clk $end
$var wire 1 " rd_en $end
$var wire 5 # rd_ptr_gray_next [4:0] $end
$var wire 1 $ rd_rst_n $end
$var wire 1 % wr_clk $end
$var wire 8 & wr_data [7:0] $end
$var wire 1 ' wr_en $end
$var wire 5 ( wr_ptr_gray_next [4:0] $end
$var wire 1 ) wr_rst_n $end
$var wire 5 * wr_ptr_bin_next [4:0] $end
$var wire 5 + rd_ptr_bin_next [4:0] $end
$var wire 1 , full_next $end
$var wire 1 - empty_next $end
$var parameter 32 . ADDR_WIDTH $end
$var parameter 32 / DATA_WIDTH $end
$var parameter 32 0 DEPTH $end
$var reg 1 1 empty $end
$var reg 1 2 full $end
$var reg 8 3 rd_data [7:0] $end
$var reg 5 4 rd_ptr_bin [4:0] $end
$var reg 5 5 rd_ptr_gray [4:0] $end
$var reg 5 6 rd_ptr_gray_sync1 [4:0] $end
$var reg 5 7 rd_ptr_gray_sync2 [4:0] $end
$var reg 5 8 wr_ptr_bin [4:0] $end
$var reg 5 9 wr_ptr_gray [4:0] $end
$var reg 5 : wr_ptr_gray_sync1 [4:0] $end
$var reg 5 ; wr_ptr_gray_sync2 [4:0] $end
$upscope $end
$enddefinitions $end
$comment Show the parameter values. $end
$dumpall
b10000 0
b1000 /
b100 .
$end
#0
$dumpvars
b0 ;
b0 :
b0 9
b0 8
b0 7
b0 6
b0 5
b0 4
b0 3
02
11
1-
0,
b0 +
b0 *
0)
b0 (
0'
b0 &
1%
0$
b0 #
0"
1!
$end
#5000
0!
0%
#10000
1!
1%
#15000
0!
0%
#20000
1!
1%
#25000
0!
0%
#30000
1$
1)
1!
1%
#35000
0!
0%
#40000
1!
1%
#45000
0!
0%
#50000
b1 (
b1 *
1'
1!
1%
#55000
0!
0%
#60000
b1 &
b11 (
b1 9
b10 *
b1 8
1!
1%
#65000
0!
0%
#70000
b10 &
b10 (
b1 :
b11 9
b11 *
b10 8
1!
1%
#75000
0!
0%
#80000
b0 &
0$
0)
0'
b10 (
0-
b1 ;
b11 :
b10 9
b11 *
b11 8
1!
1%
#85000
0!
0%
#90000
b0 (
1-
b0 ;
b0 :
b0 9
b0 *
b0 8
1!
1%
#95000
0!
0%
#100000
1!
1%
#105000
0!
0%
#110000
1!
1%
#115000
0!
0%
#120000
1$
1)
1!
1%
#125000
0!
0%
#130000
1!
1%
#135000
0!
0%
#140000
1!
1%
#140001
0$
0)
#145001
0%
#146501
0!
#150001
1%
#153001
1!
#155001
0%
#159501
0!
#160001
1%
#165001
0%
#166001
1!
#170001
1%
#172501
0!
#175001
0%
#179001
1!
#180001
1%
#185001
0%
#185501
0!
#190001
1%
#192001
1$
1)
1!
#195001
0%
#198501
0!
#200001
1%
#205001
b1 (
b1 *
b10100101 &
1'
0%
1!
#210001
0'
b1 (
b1 9
b1 *
b1 8
1%
#211501
0!
#215001
0%
#218001
b1 :
1!
#220001
1%
#224501
0!
#225001
0%
#230001
1%
#231001
0-
b1 ;
1!
#235001
0%
#237501
0!
#240001
1%
#244001
1-
b1 #
b1 +
1"
01
1!
#245001
0%
#250001
1%
#250501
0!
#255001
0%
#257001
0"
1-
b1 #
11
b10100101 3
b1 5
b1 +
b1 4
1!
#257002
b0 (
b0 9
b0 *
b0 8
1%
b0 &
0$
0)
#262002
0!
0%
#267002
b0 #
b0 3
b0 5
b0 +
b0 4
1-
b0 ;
b0 :
1!
1%
#272002
0!
0%
#277002
1!
1%
#282002
0!
0%
#287002
1!
1%
#292002
0!
0%
#297002
1$
1)
1!
1%
#302002
0!
0%
#307002
1!
1%
#312002
0!
0%
#317002
b1 (
b1 *
1'
1!
1%
#322002
0!
0%
#327002
b1 &
b11 (
b1 9
b10 *
b1 8
1!
1%
#332002
0!
0%
#337002
b10 &
b10 (
b1 :
b11 9
b11 *
b10 8
1!
1%
#342002
0!
0%
#347002
b11 &
b110 (
0-
b1 ;
b11 :
b10 9
b100 *
b11 8
1!
1%
#352002
0!
0%
#357002
b100 &
b111 (
01
b11 ;
b10 :
b110 9
b101 *
b100 8
1!
1%
#362002
0!
0%
#367002
b101 &
b101 (
b10 ;
b110 :
b111 9
b110 *
b101 8
1!
1%
#372002
0!
0%
#377002
b110 &
b100 (
b110 ;
b111 :
b101 9
b111 *
b110 8
1!
1%
#382002
0!
0%
#387002
b111 &
b1100 (
b111 ;
b101 :
b100 9
b1000 *
b111 8
1!
1%
#392002
0!
0%
#397002
b1000 &
b1101 (
b101 ;
b100 :
b1100 9
b1001 *
b1000 8
1!
1%
#402002
0!
0%
#407002
b1001 &
b1111 (
b100 ;
b1100 :
b1101 9
b1010 *
b1001 8
1!
1%
#412002
0!
0%
#417002
b1010 &
b1110 (
b1100 ;
b1101 :
b1111 9
b1011 *
b1010 8
1!
1%
#422002
0!
0%
#427002
b1011 &
b1010 (
b1101 ;
b1111 :
b1110 9
b1100 *
b1011 8
1!
1%
#432002
0!
0%
#437002
b1100 &
b1011 (
b1111 ;
b1110 :
b1010 9
b1101 *
b1100 8
1!
1%
#442002
0!
0%
#447002
b1101 &
b1001 (
b1110 ;
b1010 :
b1011 9
b1110 *
b1101 8
1!
1%
#452002
0!
0%
#457002
b1110 &
b1000 (
b1010 ;
b1011 :
b1001 9
b1111 *
b1110 8
1!
1%
#462002
0!
0%
#467002
b1111 &
1,
b11000 (
b1011 ;
b1001 :
b1000 9
b10000 *
b1111 8
1!
1%
#472002
0!
0%
#477002
0'
1,
b11000 (
b1001 ;
b1000 :
b11000 9
b10000 *
b10000 8
12
1!
1%
#477003
b0 &
0$
0)
#482003
0!
0%
#487003
0,
b0 (
1-
b0 ;
b0 :
11
02
b0 9
b0 *
b0 8
1!
1%
#492003
0!
0%
#497003
1!
1%
#502003
0!
0%
#507003
1!
1%
#512003
0!
0%
#517003
1$
1)
1!
1%
#522003
0!
0%
#527003
1!
1%
#532003
0!
0%
#537003
b1 (
b1 *
1'
1!
1%
#542003
0!
0%
#547003
b1 &
b11 (
b1 9
b10 *
b1 8
1!
1%
#552003
0!
0%
#557003
b10 &
b10 (
b1 :
b11 9
b11 *
b10 8
1!
1%
#562003
0!
0%
#567003
b11 &
b110 (
0-
b1 ;
b11 :
b10 9
b100 *
b11 8
1!
1%
#572003
0!
0%
#577003
b100 &
b111 (
01
b11 ;
b10 :
b110 9
b101 *
b100 8
1!
1%
#582003
0!
0%
#587003
b101 &
b101 (
b10 ;
b110 :
b111 9
b110 *
b101 8
1!
1%
#592003
0!
0%
#597003
b110 &
b100 (
b110 ;
b111 :
b101 9
b111 *
b110 8
1!
1%
#602003
0!
0%
#607003
b111 &
b1100 (
b111 ;
b101 :
b100 9
b1000 *
b111 8
1!
1%
#612003
0!
0%
#617003
b1000 &
b1101 (
b101 ;
b100 :
b1100 9
b1001 *
b1000 8
1!
1%
#622003
0!
0%
#627003
b1001 &
b1111 (
b100 ;
b1100 :
b1101 9
b1010 *
b1001 8
1!
1%
#632003
0!
0%
#637003
b1010 &
b1110 (
b1100 ;
b1101 :
b1111 9
b1011 *
b1010 8
1!
1%
#642003
0!
0%
#647003
b1011 &
b1010 (
b1101 ;
b1111 :
b1110 9
b1100 *
b1011 8
1!
1%
#652003
0!
0%
#657003
b1100 &
b1011 (
b1111 ;
b1110 :
b1010 9
b1101 *
b1100 8
1!
1%
#662003
0!
0%
#667003
b1101 &
b1001 (
b1110 ;
b1010 :
b1011 9
b1110 *
b1101 8
1!
1%
#672003
0!
0%
#677003
b1110 &
b1000 (
b1010 ;
b1011 :
b1001 9
b1111 *
b1110 8
1!
1%
#682003
0!
0%
#687003
b1111 &
1,
b11000 (
b1011 ;
b1001 :
b1000 9
b10000 *
b1111 8
1!
1%
#692003
0!
0%
#697003
b11111111 &
1,
b11000 (
b1001 ;
b1000 :
b11000 9
b10000 *
b10000 8
12
1!
1%
#702003
0!
0%
#707003
b1 #
b1 +
1"
0'
b1000 ;
b11000 :
1!
1%
#712003
0!
0%
#717003
0"
b1 #
b11000 ;
b1 5
b1 +
b1 4
1!
1%
#717004
b0 &
0$
0)
#722004
0!
0%
#727004
1-
b0 #
0,
b0 (
b0 5
b0 +
b0 4
b0 ;
b0 :
11
02
b0 9
b0 *
b0 8
1!
1%
#732004
0!
0%
#737004
1!
1%
#742004
0!
0%
#747004
1!
1%
#752004
0!
0%
#757004
1$
1)
1!
1%
#762004
0!
0%
#767004
1!
1%
#772004
0!
0%
#777004
1"
1!
1%
#782004
0!
0%
#787004
b1 (
b1 *
b111100 &
1'
0"
1!
1%
#792004
0!
0%
#797004
0'
b1 (
b1 9
b1 *
b1 8
1!
1%
#802004
0!
0%
#807004
b1 :
1!
1%
#812004
0!
0%
#817004
0-
b1 ;
1!
1%
#822004
0!
0%
#827004
1-
b1 #
b1 +
1"
01
1!
1%
#832004
0!
0%
#837004
0"
1-
b1 #
11
b111100 3
b1 5
b1 +
b1 4
1!
1%
#837005
b0 &
0$
0)
#842005
0!
0%
#847005
b0 #
b0 (
b0 3
b0 5
b0 +
b0 4
1-
b0 ;
b0 :
b0 9
b0 *
b0 8
1!
1%
#852005
0!
0%
#857005
1!
1%
#862005
0!
0%
#867005
1!
1%
#872005
0!
0%
#877005
1$
1)
1!
1%
#882005
0!
0%
#887005
1!
1%
#892005
0!
0%
#897005
b1 (
b1 *
1'
1!
1%
#902005
0!
0%
#907005
b1 &
b11 (
b1 9
b10 *
b1 8
1!
1%
#912005
0!
0%
#917005
b10 &
b10 (
b1 :
b11 9
b11 *
b10 8
1!
1%
#922005
0!
0%
#927005
b11 &
b110 (
0-
b1 ;
b11 :
b10 9
b100 *
b11 8
1!
1%
#932005
0!
0%
#937005
b100 &
b111 (
01
b11 ;
b10 :
b110 9
b101 *
b100 8
1!
1%
#942005
0!
0%
#947005
b101 &
b101 (
b10 ;
b110 :
b111 9
b110 *
b101 8
1!
1%
#952005
0!
0%
#957005
b110 &
b100 (
b110 ;
b111 :
b101 9
b111 *
b110 8
1!
1%
#962005
0!
0%
#967005
b111 &
b1100 (
b111 ;
b101 :
b100 9
b1000 *
b111 8
1!
1%
#972005
0!
0%
#977005
b1000 &
b1101 (
b101 ;
b100 :
b1100 9
b1001 *
b1000 8
1!
1%
#982005
0!
0%
#987005
b1001 &
b1111 (
b100 ;
b1100 :
b1101 9
b1010 *
b1001 8
1!
1%
#992005
0!
0%
#997005
b1010 &
b1110 (
b1100 ;
b1101 :
b1111 9
b1011 *
b1010 8
1!
1%
#1002005
0!
0%
#1007005
b1011 &
b1010 (
b1101 ;
b1111 :
b1110 9
b1100 *
b1011 8
1!
1%
#1012005
0!
0%
#1017005
b1100 &
b1011 (
b1111 ;
b1110 :
b1010 9
b1101 *
b1100 8
1!
1%
#1022005
0!
0%
#1027005
b1101 &
b1001 (
b1110 ;
b1010 :
b1011 9
b1110 *
b1101 8
1!
1%
#1032005
0!
0%
#1037005
b1110 &
b1000 (
b1010 ;
b1011 :
b1001 9
b1111 *
b1110 8
1!
1%
#1042005
0!
0%
#1047005
b1111 &
1,
b11000 (
b1011 ;
b1001 :
b1000 9
b10000 *
b1111 8
1!
1%
#1052005
0!
0%
#1057005
b10101010 &
1,
b11000 (
b1001 ;
b1000 :
b11000 9
b10000 *
b10000 8
12
1!
1%
#1062005
0!
0%
#1067005
b1 #
b1 +
1"
0'
b1000 ;
b11000 :
1!
1%
#1072005
0!
0%
#1077005
b11 #
b11000 ;
b1 5
b10 +
b1 4
1!
1%
#1082005
0!
0%
#1087005
b10 #
b1 3
b11 5
b11 +
b10 4
b1 6
1!
1%
#1092005
0!
0%
#1097005
0,
b110 #
b10 3
b10 5
b100 +
b11 4
b1 7
b11 6
1!
1%
#1102005
0!
0%
#1107005
b111 #
b11 3
b110 5
b101 +
b100 4
02
b11 7
b10 6
1!
1%
#1112005
0!
0%
#1117005
b101 #
b100 3
b111 5
b110 +
b101 4
b10 7
b110 6
1!
1%
#1122005
0!
0%
#1127005
b100 #
b101 3
b101 5
b111 +
b110 4
b110 7
b111 6
1!
1%
#1132005
0!
0%
#1137005
b1100 #
b110 3
b100 5
b1000 +
b111 4
b111 7
b101 6
1!
1%
#1142005
0!
0%
#1147005
b1101 #
b111 3
b1100 5
b1001 +
b1000 4
b101 7
b100 6
1!
1%
#1152005
0!
0%
#1157005
b1111 #
b1000 3
b1101 5
b1010 +
b1001 4
b100 7
b1100 6
1!
1%
#1162005
0!
0%
#1167005
b1110 #
b1001 3
b1111 5
b1011 +
b1010 4
b1100 7
b1101 6
1!
1%
#1172005
0!
0%
#1177005
b1010 #
b1010 3
b1110 5
b1100 +
b1011 4
b1101 7
b1111 6
1!
1%
#1182005
0!
0%
#1187005
b1011 #
b1011 3
b1010 5
b1101 +
b1100 4
b1111 7
b1110 6
1!
1%
#1192005
0!
0%
#1197005
b1001 #
b1100 3
b1011 5
b1110 +
b1101 4
b1110 7
b1010 6
1!
1%
#1202005
0!
0%
#1207005
b1000 #
b1101 3
b1001 5
b1111 +
b1110 4
b1010 7
b1011 6
1!
1%
#1212005
0!
0%
#1217005
1-
b11000 #
b1110 3
b1000 5
b10000 +
b1111 4
b1011 7
b1001 6
1!
1%
#1222005
0!
0%
#1227005
0"
1-
b11000 #
b1111 3
b11000 5
b10000 +
b10000 4
11
b1001 7
b1000 6
1!
1%
#1227006
b0 &
0$
0)
#1232006
0%
#1233506
0!
#1237006
b0 (
b0 9
b0 *
b0 8
b0 7
b0 6
1%
#1240006
b0 #
1-
b0 ;
b0 :
b0 3
b0 5
b0 +
b0 4
1!
#1242006
0%
#1246506
0!
#1247006
1%
#1252006
0%
#1253006
1!
#1257006
1%
#1259506
0!
#1262006
0%
#1266006
1!
#1267006
1%
#1272006
0%
#1272506
0!
#1277006
1%
#1279006
1$
1)
1!
#1282006
0%
#1285506
0!
#1287006
1%
#1292006
b1 (
b1 *
1'
0%
1!
#1297006
b1 &
b11 (
b1 9
b10 *
b1 8
1%
#1298506
0!
#1302006
0%
#1305006
b1 :
1!
#1307006
b10 &
b10 (
b11 9
b11 *
b10 8
1%
#1311506
0!
#1312006
0%
#1317006
b11 &
b110 (
b10 9
b100 *
b11 8
1%
#1318006
0-
b1 ;
b10 :
1!
#1322006
0%
#1324506
0!
#1327006
b100 &
b111 (
b110 9
b101 *
b100 8
1%
#1331006
b10 ;
b110 :
01
1!
#1332006
0%
#1337006
b101 &
b101 (
b111 9
b110 *
b101 8
1%
#1337506
0!
#1342006
0%
#1344006
b110 ;
b111 :
1!
#1347006
b110 &
b100 (
b101 9
b111 *
b110 8
1%
#1350506
0!
#1352006
0%
#1357006
b111 &
b1100 (
b100 9
b1000 *
b111 8
b111 ;
b101 :
1%
1!
#1362006
0%
#1363506
0!
#1367006
b0 &
0$
0)
0'
b1100 (
b1100 9
b1000 *
b1000 8
1%
#1370006
11
1-
b0 ;
b0 :
1!
#1372006
0%
#1376506
0!
#1377006
b0 (
b0 9
b0 *
b0 8
1%
#1382006
0%
#1383006
1!
#1387006
1%
#1389506
0!
#1392006
0%
#1396006
1!
#1397006
1%
#1402006
0%
#1402506
0!
#1407006
1%
#1409006
1$
1)
1!
#1412006
0%
#1415506
0!
#1417006
1%
#1422006
b1 (
b1 *
b1111110 &
1'
0%
1!
#1427006
0'
b1 (
b1 9
b1 *
b1 8
1%
#1428506
0!
#1432006
0%
#1435006
b1 :
1!
#1437006
1%
#1441506
0!
#1442006
0%
#1447006
1%
#1448006
0-
b1 ;
1!
#1452006
0%
#1454506
0!
#1457006
1%
#1461006
1-
b1 #
b1 +
1"
01
1!
#1462006
0%
#1467006
1%
#1467506
0!
#1472006
0%
#1474006
0"
1-
b1 #
11
b1111110 3
b1 5
b1 +
b1 4
1!
#1474007
b0 (
b0 9
b0 *
b0 8
1%
b0 &
0$
0)
#1477507
0%
#1481007
1%
#1482507
0!
#1484507
0%
#1488007
1%
#1491007
b0 #
b0 3
b0 5
b0 +
b0 4
1-
b0 ;
b0 :
1!
#1491507
0%
#1495007
1%
#1498507
0%
#1499507
0!
#1502007
1%
#1505507
0%
#1508007
1!
#1509007
1%
#1512507
0%
#1516007
1%
#1516507
0!
#1519507
0%
#1523007
1%
#1525007
1!
#1526507
0%
#1530007
1%
#1533507
0%
0!
#1537007
1%
#1540507
0%
#1542007
1$
1)
1!
#1544007
1%
#1547507
0%
#1550507
0!
#1551007
1%
#1554507
0%
#1558007
1%
#1559007
1!
#1561507
0%
#1565007
b1 (
b1 *
b1100 &
1'
1%
#1567507
0!
#1568507
0%
#1572007
0'
b1 (
b1 9
b1 *
b1 8
1%
#1575507
0%
#1576007
b1 :
1!
#1579007
b11 (
b10 *
b110100 &
1'
1%
#1582507
0%
#1584507
0!
#1586007
b101100 &
b10 (
b11 9
b11 *
b10 8
1%
#1589507
0%
#1593007
b101111 &
b110 (
b10 9
b100 *
b11 8
0-
b1 ;
b11 :
1%
1!
#1596507
0%
#1600007
b1101 &
b111 (
b110 9
b101 *
b100 8
1%
#1601507
0!
#1603507
0%
#1607007
b11010110 &
b101 (
b111 9
b110 *
b101 8
1%
#1610007
b1 #
b1 +
1"
01
b11 ;
b111 :
1!
#1610507
0%
#1614007
b11 &
b100 (
b101 9
b111 *
b110 8
1%
#1617507
0%
#1618507
0!
#1621007
0'
b100 (
b100 9
b111 *
b111 8
1%
#1624507
0%
#1627007
b11 #
b1100 3
b1 5
b10 +
b1 4
b111 ;
b100 :
1!
#1628007
b1100 (
b1000 *
b10001110 &
1'
b1 6
1%
#1631507
0%
#1635007
b10101100 &
b1101 (
b1 7
b1100 9
b1001 *
b1000 8
1%
#1635507
0!
#1638507
0%
#1642007
b11000010 &
b1111 (
b1101 9
b1010 *
b1001 8
1%
#1644007
b10 #
b100 ;
b1101 :
b110100 3
b11 5
b11 +
b10 4
1!
#1645507
0%
#1649007
0'
b1111 (
b11 6
b1111 9
b1010 *
b1010 8
1%
#1652507
0%
0!
#1656007
b1110 (
b1011 *
b10110 &
1'
b11 7
1%
#1659507
0%
#1661007
0"
b10 #
b101100 3
b10 5
b11 +
b11 4
b1101 ;
b1111 :
1!
#1663007
b11000001 &
b1010 (
b10 6
b1110 9
b1100 *
b1011 8
1%
#1666507
0%
#1669507
0!
#1670007
b10010110 &
b1011 (
b1010 9
b1101 *
b1100 8
b10 7
1%
#1673507
0%
#1677007
0'
b1011 (
b1011 9
b1101 *
b1101 8
1%
#1678007
b110 #
b100 +
1"
b1111 ;
b1011 :
1!
#1680507
0%
#1684007
1%
#1686507
0!
#1687507
0%
#1691007
b1001 (
b1110 *
b100011 &
1'
1%
#1694507
0%
#1695007
b111 #
b101111 3
b110 5
b101 +
b100 4
b1011 ;
1!
#1698007
b10010100 &
b1000 (
b1001 9
b1111 *
b1110 8
b110 6
1%
#1701507
0%
#1703507
0!
#1705007
0'
b1000 (
b110 7
b1000 9
b1111 *
b1111 8
1%
#1708507
0%
#1712007
0"
b111 #
b1000 :
b1101 3
b111 5
b101 +
b101 4
1%
1!
#1715507
0%
#1719007
b11000 (
b10000 *
b11101000 &
1'
b111 6
1%
#1720507
0!
#1722507
0%
#1726007
b10111010 &
b11001 (
b11000 9
b10001 *
b10000 8
b111 7
1%
#1729007
b101 #
b110 +
1"
b1000 ;
b11000 :
1!
#1729507
0%
#1733007
b10001000 &
b11011 (
b11001 9
b10010 *
b10001 8
1%
#1736507
0%
#1737507
0!
#1740007
0'
b11011 (
b11011 9
b10010 *
b10010 8
1%
#1743507
0%
#1746007
b100 #
b11000 ;
b11011 :
b11010110 3
b101 5
b111 +
b110 4
1!
#1747007
b11010 (
b10011 *
b1010111 &
1'
b101 6
1%
#1750507
0%
#1754007
b1111101 &
0,
b11110 (
b11010 9
b10100 *
b10011 8
b101 7
1%
#1754507
0!
#1757507
0%
#1761007
b11000010 &
b11111 (
b11110 9
b10101 *
b10100 8
1%
#1763007
b1100 #
b11 3
b100 5
b1000 +
b111 4
b11011 ;
b11110 :
1!
#1764507
0%
#1768007
0'
0,
b11111 (
b11111 9
b10101 *
b10101 8
b100 6
1%
#1771507
0%
0!
#1775007
0,
b11101 (
b10110 *
b1110000 &
1'
b100 7
1%
#1778507
0%
#1780007
b1101 #
b11110 ;
b11111 :
b10001110 3
b1100 5
b1001 +
b1000 4
1!
#1782007
0'
0,
b11101 (
b11101 9
b10110 *
b10110 8
b1100 6
1%
#1785507
0%
#1788507
0!
#1789007
b1100 7
1%
#1792507
0%
#1796007
b11100 (
b10111 *
b10000 &
1'
1%
#1797007
0"
b1101 #
b10101100 3
b1101 5
b1001 +
b1001 4
b11111 ;
b11101 :
1!
#1799507
0%
#1803007
b100001 &
1,
b10100 (
b1101 6
b11100 9
b11000 *
b10111 8
1%
#1805507
0!
#1806507
0%
#1810007
b10100001 &
0,
b10100 (
b10100 9
b11000 *
b11000 8
b1101 7
12
1%
#1813507
0%
#1814007
b1111 #
b1010 +
1"
b11101 ;
b10100 :
1!
#1817007
b11101010 &
1,
b10101 (
b11001 *
02
1%
#1820507
0%
#1822507
0!
#1824007
b1000111 &
1,
b10101 (
b10101 9
b11001 *
b11001 8
12
1%
#1827507
0%
#1831007
b10000110 &
b1110 #
b11000010 3
b1111 5
b1011 +
b1010 4
b10100 ;
b10101 :
1%
1!
#1834507
0%
#1838007
0'
b1111 6
1%
#1839507
0!
#1841507
0%
#1845007
b11001100 &
1'
0,
b1111 7
1%
#1848007
b1010 #
b10101 ;
b10110 3
b1110 5
b1100 +
b1011 4
1!
#1848507
0%
#1852007
0'
0,
b10101 (
b11001 *
b1110 6
02
1%
#1855507
0%
#1856507
0!
#1859007
0,
b10111 (
b11010 *
b11111100 &
1'
b1110 7
1%
#1862507
0%
#1865007
b1011 #
b11000001 3
b1010 5
b1101 +
b1100 4
1!
#1866007
b111000 &
1,
b10110 (
b10111 9
b11011 *
b11010 8
b1010 6
1%
#1869507
0%
#1873007
b1010001 &
0,
b10110 (
12
b1010 7
b10110 9
b11011 *
b11011 8
1%
#1873507
0!
#1876507
0%
#1880007
0'
0,
b10110 (
b11011 *
02
1%
#1882007
b1001 #
b10110 :
b10010110 3
b1011 5
b1110 +
b1101 4
1!
#1883507
0%
#1887007
1,
b10010 (
b11100 *
b11000011 &
1'
b1011 6
1%
#1890507
0%
0!
#1894007
b11101111 &
0,
b10010 (
b10010 9
b11100 *
b11100 8
b1011 7
12
1%
#1897507
0%
#1899007
b1000 #
b100011 3
b1001 5
b1111 +
b1110 4
b10110 ;
b10010 :
1!
#1901007
0'
0,
b10010 (
b11100 *
02
b1001 6
1%
#1904507
0%
#1907507
0!
#1908007
b1001 7
1%
#1911507
0%
#1915007
b10011 (
b11101 *
b111010 &
1'
1%
#1916007
b11000 #
b10010 ;
b10010100 3
b1000 5
b10000 +
b1111 4
1!
#1918507
0%
#1922007
b10001000 &
1,
b10001 (
b10011 9
b11110 *
b11101 8
b1000 6
1%
#1924507
0!
#1925507
0%
#1929007
0'
0,
b10001 (
12
b1000 7
b10001 9
b11110 *
b11110 8
1%
#1932507
0%
#1933007
b11001 #
b11101000 3
b11000 5
b10001 +
b10000 4
b10001 :
1!
#1936007
1,
b10000 (
b11111 *
b1010000 &
1'
b11000 6
02
1%
#1939507
0%
#1941507
0!
#1943007
b10000110 &
0,
b10000 (
12
b11000 7
b10000 9
b11111 *
b11111 8
1%
#1946507
0%
#1950007
0'
0"
0,
b10000 (
b11111 *
b11001 #
02
b10001 ;
b10000 :
b10111010 3
b11001 5
b10001 +
b10001 4
1%
1!
#1953507
0%
#1957007
1,
b0 (
b0 *
b110110 &
1'
b11001 6
1%
#1958507
0!
#1960507
0%
#1964007
0'
0,
b0 (
b0 9
b0 *
b0 8
b11001 7
12
1%
#1967007
b11011 #
b10010 +
1"
b10000 ;
b0 :
1!
#1967507
0%
#1971007
1,
b1 (
b1 *
b1100101 &
1'
02
1%
#1974507
0%
#1975507
0!
