rtl/sync_fifo.v
// sync_fifo.v -- Parameterized synchronous FIFO.
//
// Pointer-based implementation: write and read pointers are each
// ADDR_WIDTH+1 bits wide. The extra (MSB) bit never participates in the
// memory address -- it only exists to disambiguate "full" from "empty"
// when the lower ADDR_WIDTH bits of both pointers are equal, which
// happens in both cases for a plain ADDR_WIDTH-bit pointer. This is the
// standard approach (vs. a fill-count counter) because it needs no extra
// adder/comparator beyond the pointer increments themselves, and the
// full/empty conditions fall out of simple XOR/equality checks on the
// pointers directly.
//
// IEEE 1364-2005 only (no SystemVerilog constructs) -- compiled with
// `-g2005` in the Makefile to enforce this at build time, not just by
// convention.

module sync_fifo #(
    parameter DATA_WIDTH = 8,
    parameter DEPTH      = 16   // must be a power of 2
) (
    input  wire                  clk,
    input  wire                  rst_n,     // active-low, synchronous
    input  wire                  wr_en,
    input  wire [DATA_WIDTH-1:0] wr_data,
    input  wire                  rd_en,
    output reg  [DATA_WIDTH-1:0] rd_data,
    output wire                  full,
    output wire                  empty
);

    localparam ADDR_WIDTH = $clog2(DEPTH);

    reg [DATA_WIDTH-1:0] mem [0:DEPTH-1];

    // Pointers carry one extra bit beyond the memory address width.
    reg [ADDR_WIDTH:0] wr_ptr;
    reg [ADDR_WIDTH:0] rd_ptr;

    wire [ADDR_WIDTH-1:0] wr_addr;
    wire [ADDR_WIDTH-1:0] rd_addr;

    assign wr_addr = wr_ptr[ADDR_WIDTH-1:0];
    assign rd_addr = rd_ptr[ADDR_WIDTH-1:0];

    // empty: pointers fully match (both address bits and the wrap bit).
    // full: address bits match but the wrap bit differs -- the write
    // pointer has lapped the read pointer exactly once.
    assign empty = (wr_ptr == rd_ptr);
    assign full  = (wr_addr == rd_addr) && (wr_ptr[ADDR_WIDTH] != rd_ptr[ADDR_WIDTH]);

    always @(posedge clk) begin
        if (!rst_n) begin
            wr_ptr <= {(ADDR_WIDTH+1){1'b0}};
        end else if (wr_en && !full) begin
            mem[wr_addr] <= wr_data;
            wr_ptr        <= wr_ptr + 1'b1;
        end
    end

    always @(posedge clk) begin
        if (!rst_n) begin
            rd_ptr  <= {(ADDR_WIDTH+1){1'b0}};
            rd_data <= {DATA_WIDTH{1'b0}};
        end else if (rd_en && !empty) begin
            rd_data <= mem[rd_addr];
            rd_ptr  <= rd_ptr + 1'b1;
        end
    end

endmodule

results/waves.vcd
$date
	Sat Sep 12 23:49:14 2026
$end
$version
	Icarus Verilog
$end
$timescale
	1ps
$end
$scope module sync_fifo $end
$var wire 1 ! clk $end
$var wire 1 " full $end
$var wire 1 # rd_en $end
$var wire 1 $ rst_n $end
$var wire 8 % wr_data [7:0] $end
$var wire 1 & wr_en $end
$var wire 4 ' wr_addr [3:0] $end
$var wire 4 ( rd_addr [3:0] $end
$var wire 1 ) empty $end
$var parameter 32 * ADDR_WIDTH $end
$var parameter 32 + DATA_WIDTH $end
$var parameter 32 , DEPTH $end
$var reg 8 - rd_data [7:0] $end
$var reg 5 . rd_ptr [4:0] $end
$var reg 5 / wr_ptr [4:0] $end
$upscope $end
$enddefinitions $end
$comment Show the parameter values. $end
$dumpall
b10000 ,
b1000 +
b100 *
$end
#0
$dumpvars
b0 /
b0 .
b0 -
1)
b0 (
b0 '
0&
b0 %
0$
0#
0"
1!
$end
#5000
0!
#10000
1$
1!
#15000
0!
#20000
1&
1!
#25000
0!
#30000
b1 %
b1 '
0)
b1 /
1!
#35000
0!
#40000
b10 %
b10 '
b10 /
1!
#45000
0!
#50000
b0 %
0$
0&
b11 '
b11 /
1!
#55000
0!
#60000
b0 '
1)
b0 /
1!
#65000
0!
#70000
1$
1!
#75000
0!
#80000
1!
#80001
0$
#85001
0!
#90001
1!
#95001
0!
#100001
1$
1!
#105001
0!
#110001
b10100101 %
1&
1!
#115001
0!
#120001
1#
0&
b1 '
0)
b1 /
1!
#125001
0!
#130001
0#
b1 (
1)
b1 .
b10100101 -
1!
#130002
b0 %
0$
#135002
0!
#140002
b0 '
b0 (
b0 /
b0 -
1)
b0 .
1!
#145002
0!
#150002
1$
1!
#155002
0!
#160002
1&
1!
#165002
0!
#170002
b1 %
b1 '
0)
b1 /
1!
#175002
0!
#180002
b10 %
b10 '
b10 /
1!
#185002
0!
#190002
b11 %
b11 '
b11 /
1!
#195002
0!
#200002
b100 %
b100 '
b100 /
1!
#205002
0!
#210002
b101 %
b101 '
b101 /
1!
#215002
0!
#220002
b110 %
b110 '
b110 /
1!
#225002
0!
#230002
b111 %
b111 '
b111 /
1!
#235002
0!
#240002
b1000 %
b1000 '
b1000 /
1!
#245002
0!
#250002
b1001 %
b1001 '
b1001 /
1!
#255002
0!
#260002
b1010 %
b1010 '
b1010 /
1!
#265002
0!
#270002
b1011 %
b1011 '
b1011 /
1!
#275002
0!
#280002
b1100 %
b1100 '
b1100 /
1!
#285002
0!
#290002
b1101 %
b1101 '
b1101 /
1!
#295002
0!
#300002
b1110 %
b1110 '
b1110 /
1!
#305002
0!
#310002
b1111 %
b1111 '
b1111 /
1!
#315002
0!
#320002
0&
1"
b0 '
b10000 /
1!
#320003
b0 %
0$
#325003
0!
#330003
0"
1)
b0 /
1!
#335003
0!
#340003
1$
1!
#345003
0!
#350003
1&
1!
#355003
0!
#360003
b1 %
b1 '
0)
b1 /
1!
#365003
0!
#370003
b10 %
b10 '
b10 /
1!
#375003
0!
#380003
b11 %
b11 '
b11 /
1!
#385003
0!
#390003
b100 %
b100 '
b100 /
1!
#395003
0!
#400003
b101 %
b101 '
b101 /
1!
#405003
0!
#410003
b110 %
b110 '
b110 /
1!
#415003
0!
#420003
b111 %
b111 '
b111 /
1!
#425003
0!
#430003
b1000 %
b1000 '
b1000 /
1!
#435003
0!
#440003
b1001 %
b1001 '
b1001 /
1!
#445003
0!
#450003
b1010 %
b1010 '
b1010 /
1!
#455003
0!
#460003
b1011 %
b1011 '
b1011 /
1!
#465003
0!
#470003
b1100 %
b1100 '
b1100 /
1!
#475003
0!
#480003
b1101 %
b1101 '
b1101 /
1!
#485003
0!
#490003
b1110 %
b1110 '
b1110 /
1!
#495003
0!
#500003
b1111 %
b1111 '
b1111 /
1!
#505003
0!
#510003
b11111111 %
1"
b0 '
b10000 /
1!
#515003
0!
#520003
1#
0&
1!
#525003
0!
#530003
0#
0"
b1 (
b1 .
1!
#530004
b0 %
0$
#535004
0!
#540004
0"
b0 (
1)
b0 /
b0 .
1!
#545004
0!
#550004
1$
1!
#555004
0!
#560004
1#
1!
#565004
0!
#570004
b111100 %
1&
0#
1!
#575004
0!
#580004
1#
0&
b1 '
0)
b1 /
1!
#585004
0!
#590004
0#
b1 (
1)
b1 .
b111100 -
1!
#590005
b0 %
0$
#595005
0!
#600005
b0 '
b0 (
b0 /
b0 -
1)
b0 .
1!
#605005
0!
#610005
1$
1!
#615005
0!
#620005
b10001 %
1&
1!
#625005
0!
#630005
1#
b100010 %
b1 '
0)
b1 /
1!
#635005
0!
#640005
1#
0&
b10 '
b1 (
b10 /
0)
b1 .
b10001 -
1!
#645005
0!
#650005
0#
b10 (
1)
b10 .
b100010 -
1!
#650006
b0 %
0$
#655006
0!
#660006
b0 '
b0 (
b0 /
b0 -
1)
b0 .
1!
#665006
0!
#670006
1$
1!
#675006
0!
#680006
1&
1!
#685006
0!
#690006
b1 %
b1 '
0)
b1 /
1!
#695006
0!
#700006
b10 %
b10 '
b10 /
1!
#705006
0!
#710006
b11 %
b11 '
b11 /
1!
#715006
0!
#720006
b100 %
b100 '
b100 /
1!
#725006
0!
#730006
b101 %
b101 '
b101 /
1!
#735006
0!
#740006
b110 %
b110 '
b110 /
1!
#745006
0!
#750006
b111 %
b111 '
b111 /
1!
#755006
0!
#760006
b0 %
0$
0&
b1000 '
b1000 /
1!
#765006
0!
#770006
b0 '
1)
b0 /
1!
#775006
0!
#780006
1$
1!
#785006
0!
#790006
b1111110 %
1&
1!
#795006
0!
#800006
1#
0&
b1 '
0)
b1 /
1!
#805006
0!
#810006
0#
b1 (
1)
b1 .
b1111110 -
1!
#810007
b0 %
0$
#815007
0!
#820007
b0 '
b0 (
b0 /
b0 -
1)
b0 .
1!
#825007
0!
#830007
1$
1!
#835007
0!
#840007
1&
1!
#845007
0!
#850007
1#
b1 %
b1 '
0)
b1 /
1!
#855007
0!
#860007
b10 %
b10 '
b1 (
b10 /
0)
b1 .
1!
#865007
0!
#870007
b11 %
b10 (
b11 '
b10 .
b1 -
b11 /
1!
#875007
0!
#880007
b100 %
b100 '
b11 (
b100 /
0)
b11 .
b10 -
1!
#885007
0!
#890007
b101 %
b100 (
b101 '
b100 .
b11 -
b101 /
1!
#895007
0!
#900007
b110 %
b110 '
b101 (
b110 /
0)
b101 .
b100 -
1!
#905007
0!
#910007
b111 %
b110 (
b111 '
b110 .
b101 -
b111 /
1!
#915007
0!
#920007
b1000 %
b1000 '
b111 (
b1000 /
0)
b111 .
b110 -
1!
#925007
0!
#930007
b1001 %
b1000 (
b1001 '
b1000 .
b111 -
b1001 /
1!
#935007
0!
#940007
b1010 %
b1010 '
b1001 (
b1010 /
0)
b1001 .
b1000 -
1!
#945007
0!
#950007
b1011 %
b1010 (
b1011 '
b1010 .
b1001 -
b1011 /
1!
#955007
0!
#960007
b1100 %
b1100 '
b1011 (
b1100 /
0)
b1011 .
b1010 -
1!
#965007
0!
#970007
b1101 %
b1100 (
b1101 '
b1100 .
b1011 -
b1101 /
1!
#975007
0!
#980007
b1110 %
b1110 '
b1101 (
b1110 /
0)
b1101 .
b1100 -
1!
#985007
0!
#990007
b1111 %
b1110 (
b1111 '
b1110 .
b1101 -
b1111 /
1!
#995007
0!
#1000007
b10000 %
b0 '
b1111 (
b10000 /
0)
b1111 .
b1110 -
1!
#1005007
0!
#1010007
b10001 %
b0 (
b1 '
b10000 .
b1111 -
b10001 /
1!
#1015007
0!
#1020007
b10010 %
b10 '
b1 (
b10010 /
0)
b10001 .
b10000 -
1!
#1025007
0!
#1030007
b10011 %
b10 (
b11 '
b10010 .
b10001 -
b10011 /
1!
#1035007
0!
#1040007
b10100 %
b100 '
b11 (
b10100 /
0)
b10011 .
b10010 -
1!
#1045007
0!
#1050007
b10101 %
b100 (
b101 '
b10100 .
b10011 -
b10101 /
1!
#1055007
0!
#1060007
b10110 %
b110 '
b101 (
b10110 /
0)
b10101 .
b10100 -
1!
#1065007
0!
#1070007
b10111 %
b110 (
b111 '
b10110 .
b10101 -
b10111 /
1!
#1075007
0!
#1080007
b11000 %
b1000 '
b111 (
b11000 /
0)
b10111 .
b10110 -
1!
#1085007
0!
#1090007
b11001 %
b1000 (
b1001 '
b11000 .
b10111 -
b11001 /
1!
#1095007
0!
#1100007
b11010 %
b1010 '
b1001 (
b11010 /
0)
b11001 .
b11000 -
1!
#1105007
0!
#1110007
b11011 %
b1010 (
b1011 '
b11010 .
b11001 -
b11011 /
1!
#1115007
0!
#1120007
b11100 %
b1100 '
b1011 (
b11100 /
0)
b11011 .
b11010 -
1!
#1125007
0!
#1130007
b11101 %
b1100 (
b1101 '
b11100 .
b11011 -
b11101 /
1!
#1135007
0!
#1140007
b11110 %
b1110 '
b1101 (
b11110 /
0)
b11101 .
b11100 -
1!
#1145007
0!
#1150007
b11111 %
b1110 (
b1111 '
b11110 .
b11101 -
b11111 /
1!
#1155007
0!
#1160007
b100000 %
b0 '
b1111 (
b0 /
0)
b11111 .
b11110 -
1!
#1165007
0!
#1170007
b100001 %
b0 (
b1 '
b0 .
b11111 -
b1 /
1!
#1175007
0!
#1180007
b100010 %
b10 '
b1 (
b10 /
0)
b1 .
b100000 -
1!
#1185007
0!
#1190007
b100011 %
b10 (
b11 '
b10 .
b100001 -
b11 /
1!
#1195007
0!
#1200007
b100100 %
b100 '
b11 (
b100 /
0)
b11 .
b100010 -
1!
#1205007
0!
#1210007
b100101 %
b100 (
b101 '
b100 .
b100011 -
b101 /
1!
#1215007
0!
#1220007
b100110 %
b110 '
b101 (
b110 /
0)
b101 .
b100100 -
1!
#1225007
0!
#1230007
b100111 %
b110 (
b111 '
b110 .
b100101 -
b111 /
1!
#1235007
0!
#1240007
b101000 %
b1000 '
b111 (
b1000 /
0)
b111 .
b100110 -
1!
#1245007
0!
#1250007
b101001 %
b1000 (
b1001 '
b1000 .
b100111 -
b1001 /
1!
#1255007
0!
#1260007
b101010 %
b1010 '
b1001 (
b1010 /
0)
b1001 .
b101000 -
1!
#1265007
0!
#1270007
b101011 %
b1010 (
b1011 '
b1010 .
b101001 -
b1011 /
1!
#1275007
0!
#1280007
b101100 %
b1100 '
b1011 (
b1100 /
0)
b1011 .
b101010 -
1!
#1285007
0!
#1290007
b101101 %
b1100 (
b1101 '
b1100 .
b101011 -
b1101 /
1!
#1295007
0!
#1300007
b101110 %
b1110 '
b1101 (
b1110 /
0)
b1101 .
b101100 -
1!
#1305007
0!
#1310007
b101111 %
b1110 (
b1111 '
b1110 .
b101101 -
b1111 /
1!
#1315007
0!
#1320007
b110000 %
b0 '
b1111 (
b10000 /
0)
b1111 .
b101110 -
1!
#1325007
0!
#1330007
b110001 %
b0 (
b1 '
b10000 .
b101111 -
b10001 /
1!
#1335007
0!
#1340007
b110010 %
b10 '
b1 (
b10010 /
0)
b10001 .
b110000 -
1!
#1345007
0!
#1350007
b110011 %
b10 (
b11 '
b10010 .
b110001 -
b10011 /
1!
#1355007
0!
#1360007
b110100 %
b100 '
b11 (
b10100 /
0)
b10011 .
b110010 -
1!
#1365007
0!
#1370007
b110101 %
b100 (
b101 '
b10100 .
b110011 -
b10101 /
1!
#1375007
0!
#1380007
b110110 %
b110 '
b101 (
b10110 /
0)
b10101 .
b110100 -
1!
#1385007
0!
#1390007
b110111 %
b110 (
b111 '
b10110 .
b110101 -
b10111 /
1!
#1395007
0!
#1400007
b111000 %
b1000 '
b111 (
b11000 /
0)
b10111 .
b110110 -
1!
#1405007
0!
#1410007
b111001 %
b1000 (
b1001 '
b11000 .
b110111 -
b11001 /
1!
#1415007
0!
#1420007
b111010 %
b1010 '
b1001 (
b11010 /
0)
b11001 .
b111000 -
1!
#1425007
0!
#1430007
b111011 %
b1010 (
b1011 '
b11010 .
b111001 -
b11011 /
1!
#1435007
0!
#1440007
b111100 %
b1100 '
b1011 (
b11100 /
0)
b11011 .
b111010 -
1!
#1445007
0!
#1450007
b111101 %
b1100 (
b1101 '
b11100 .
b111011 -
b11101 /
1!
#1455007
0!
#1460007
b111110 %
b1110 '
b1101 (
b11110 /
0)
b11101 .
b111100 -
1!
#1465007
0!
#1470007
b111111 %
b1110 (
b1111 '
b11110 .
b111101 -
b11111 /
1!
#1475007
0!
#1480007
b1000000 %
b0 '
b1111 (
b0 /
0)
b11111 .
b111110 -
1!
#1485007
0!
#1490007
0#
0&
b0 (
b1 '
b0 .
b111111 -
b1 /
1!
#1490008
b0 %
0$
#1495008
0!
#1500008
b0 '
1)
b0 /
b0 -
1!
#1505008
0!
#1510008
1$
1!
#1515008
0!
#1520008
1&
1!
#1525008
0!
#1530008
b1 %
b1 '
0)
b1 /
1!
#1535008
0!
#1540008
b10 %
b10 '
b10 /
1!
#1545008
0!
#1550008
b11 %
b11 '
b11 /
1!
#1555008
0!
#1560008
b100 %
b100 '
b100 /
1!
#1565008
0!
#1570008
b101 %
b101 '
b101 /
1!
#1575008
0!
#1580008
b110 %
b110 '
b110 /
1!
#1585008
0!
#1590008
b111 %
b111 '
b111 /
1!
#1595008
0!
#1600008
b1000 %
b1000 '
b1000 /
1!
#1605008
0!
#1610008
b1001 %
b1001 '
b1001 /
1!
#1615008
0!
#1620008
b1010 %
b1010 '
b1010 /
1!
#1625008
0!
#1630008
b1011 %
b1011 '
b1011 /
1!
#1635008
0!
#1640008
b1100 %
b1100 '
b1100 /
1!
#1645008
0!
#1650008
b1101 %
b1101 '
b1101 /
1!
#1655008
0!
#1660008
b1110 %
b1110 '
b1110 /
1!
#1665008
0!
#1670008
b1111 %
b1111 '
b1111 /
1!
#1675008
0!
#1680008
b10101010 %
1"
b0 '
b10000 /
1!
#1685008
0!
#1690008
1#
0&
1!
#1695008
0!
#1700008
0"
b1 (
b1 .
1!
#1705008
0!
#1710008
b10 (
b10 .
b1 -
1!
#1715008
0!
#1720008
b11 (
b11 .
b10 -
1!
#1725008
0!
#1730008
b100 (
b100 .
b11 -
1!
#1735008
0!
#1740008
b101 (
b101 .
b100 -
1!
#1745008
0!
#1750008
b110 (
b110 .
b101 -
1!
#1755008
0!
#1760008
b111 (
b111 .
b110 -
1!
#1765008
0!
#1770008
b1000 (
b1000 .
b111 -
1!
#1775008
0!
#1780008
b1001 (
b1001 .
b1000 -
1!
#1785008
0!
#1790008
b1010 (
b1010 .
b1001 -
1!
#1795008
0!
#1800008
b1011 (
b1011 .
b1010 -
1!
#1805008
0!
#1810008
b1100 (
b1100 .
b1011 -
1!
#1815008
0!
#1820008
b1101 (
b1101 .
b1100 -
1!
#1825008
0!
#1830008
b1110 (
b1110 .
b1101 -
1!
#1835008
0!
#1840008
b1111 (
b1111 .
b1110 -
1!
#1845008
0!
#1850008
0#
b0 (
1)
b10000 .
b1111 -
1!
#1850009
b0 %
0$
#1855009
0!
#1860009
b0 /
b0 -
1)
b0 .
1!
#1865009
0!
#1870009
1$
1!
#1875009
0!
#1880009
1#
b1110010 %
1&
1!
#1885009
0!
#1890009
0#
b101100 %
b1 '
0)
b1 /
1!
#1895009
0!
#1900009
1#
b1110111 %
b10 '
b10 /
1!
#1905009
0!
#1910009
b11010110 %
b1 (
b11 '
b1 .
b1110010 -
b11 /
1!
#1915009
0!
#1920009
0#
b0 %
0&
b100 '
b10 (
b100 /
b10 .
b101100 -
1!
#1925009
0!
#1930009
0$
1!
#1935009
0!
#1940009
1#
1$
b0 '
b0 (
1)
b0 /
b0 -
b0 .
1!
#1945009
0!
#1950009
1!
#1955009
0!
#1960009
0#
b10000111 %
1&
1!
#1965009
0!
#1970009
b0 %
0&
b1 '
0)
b1 /
1!
#1975009
0!
#1980009
b10111001 %
1&
1!
#1985009
0!
#1990009
1#
b0 %
0&
b10 '
b10 /
1!
#1995009
0!
#2000009
b1110111 %
1&
b1 (
b1 .
b10000111 -
1!
#2005009
0!
#2010009
b10111010 %
b10 (
b11 '
b10 .
b10111001 -
b11 /
1!
#2015009
0!
#2020009
0#
b100100 %
b100 '
b11 (
b100 /
0)
b11 .
b1110111 -
1!
#2025009
0!
#2030009
b1010011 %
b101 '
b101 /
1!
#2035009
0!
#2040009
b1110000 %
b110 '
b110 /
1!
#2045009
0!
#2050009
b0 %
0&
b111 '
b111 /
1!
#2055009
0!
#2060009
1#
b10001001 %
1&
1!
#2065009
0!
#2070009
0#
b0 %
0&
b100 (
b1000 '
b100 .
b10111010 -
b1000 /
1!
#2075009
0!
#2080009
1#
b11101010 %
1&
1!
#2085009
0!
#2090009
0#
b10000110 %
b101 (
b1001 '
b101 .
b100100 -
b1001 /
1!
#2095009
0!
#2100009
b10111001 %
b1010 '
b1010 /
1!
#2105009
0!
#2110009
b0 %
0&
b1011 '
b1011 /
1!
#2115009
0!
#2120009
1#
b1010001 %
1&
1!
#2125009
0!
#2130009
b11000011 %
b110 (
b1100 '
b110 .
b1010011 -
b1100 /
1!
#2135009
0!
#2140009
b101 %
b1101 '
b111 (
b1101 /
b111 .
b1110000 -
1!
#2145009
0!
#2150009
0#
b10001000 %
b1000 (
b1110 '
b1000 .
b10001001 -
b1110 /
1!
#2155009
0!
#2160009
1#
b1010000 %
b1111 '
b1111 /
1!
#2165009
0!
#2170009
0#
b0 %
0&
b1001 (
b0 '
b1001 .
b11101010 -
b10000 /
1!
#2175009
0!
#2180009
1#
1!
#2185009
0!
#2190009
b1010 (
b1010 .
b10000110 -
1!
#2195009
0!
#2200009
b1011 (
b1011 .
b10111001 -
1!
#2205009
0!
#2210009
0#
b1100 (
b1100 .
b1010001 -
1!
#2215009
0!
#2220009
1#
b1001 %
1&
1!
#2225009
0!
#2230009
0#
b10011101 %
b1101 (
b1 '
b1101 .
b11000011 -
b10001 /
1!
#2235009
0!
#2240009
b101000 %
b10 '
b10010 /
1!
#2245009
0!
#2250009
1#
b1000000 %
b11 '
b10011 /
1!
#2255009
0!
#2260009
0#
b10000111 %
b100 '
b1110 (
b10100 /
b1110 .
b101 -
1!
#2265009
0!
#2270009
b0 %
0&
b101 '
b10101 /
1!
#2275009
0!
#2280009
1!
#2285009
0!
#2290009
b10111111 %
1&
1!
#2295009
0!
#2300009
1#
b0 %
0&
b110 '
b10110 /
1!
#2305009
0!
#2310009
0#
b1110101 %
1&
b1111 (
b1111 .
b10001000 -
1!
#2315009
0!
#2320009
b11110 %
b111 '
b10111 /
1!
#2325009
0!
#2330009
b0 %
0&
b1000 '
b11000 /
1!
#2335009
0!
#2340009
b1101101 %
1&
1!
#2345009
0!
#2350009
b0 %
0&
b1001 '
b11001 /
1!
#2355009
0!
#2360009
1#
b11010000 %
1&
1!
#2365009
0!
#2370009
b11011000 %
b0 (
b1010 '
b10000 .
b1010000 -
b11010 /
1!
#2375009
0!
#2380009
b0 %
0&
b1011 '
b1 (
b11011 /
b10001 .
b1001 -
1!
#2385009
0!
#2390009
b10 (
b10010 .
b10011101 -
1!
#2395009
0!
#2400009
b11 (
b10011 .
b101000 -
1!
#2405009
0!
#2410009
b100 (
b10100 .
b1000000 -
1!
#2415009
0!
#2420009
0#
b100110 %
1&
b101 (
b10101 .
b10000111 -
1!
#2425009
0!
#2430009
b0 %
0&
b1100 '
b11100 /
1!
#2435009
0!
#2440009
1!
#2445009
0!
#2450009
1!
#2455009
0!
#2460009
1#
b11001101 %
1&
1!
#2465009
0!
#2470009
b11000111 %
b110 (
b1101 '
b10110 .
b10111111 -
b11101 /
1!
#2475009
0!
#2480009
b0 %
0&
b1110 '
b111 (
b11110 /
b10111 .
b1110101 -
1!
#2485009
0!
#2490009
0#
b1000 (
b11000 .
b11110 -
1!
#2495009
0!
#2500009
1#
1!
#2505009
0!
#2510009
0#
b1001 (
b11001 .
b1101101 -
1!
#2515009
0!
#2520009
1#
1!
#2525009
0!
#2530009
0#
b1010 (
b11010 .
b11010000 -
1!
#2535009
0!
#2540009
1#
1!
#2545009
0!
#2550009
0#
b1011 (
b11011 .
b11011000 -
1!
#2555009
0!
#2560009
b1111110 %
1&
1!
#2565009
0!
#2570009
1#
b10100001 %
b1111 '
b11111 /
1!
#2575009
0!
#2580009
0#
b1111010 %
b0 '
b1100 (
b0 /
b11100 .
b100110 -
1!
#2585009
0!
#2590009
b11101010 %
b1 '
b1 /
1!
#2595009
0!
#2600009
1#
b0 %
0&
b10 '
b10 /
1!
#2605009
0!
#2610009
0#
b1101 (
b11101 .
b11001101 -
1!
#2615009
0!
#2620009
1#
b10110010 %
1&
1!
#2625009
0!
#2630009
b0 %
0&
b1110 (
b11 '
b11110 .
b11000111 -
b11 /
1!
#2635009
0!
#2640009
0#
b1111 (
b11111 .
b1111110 -
1!
#2645009
0!
#2650009
1!
#2655009
0!
#2660009
0$
1!
#2665009
0!
#2670009
b1000100 %
1&
1$
b0 (
b0 '
b0 -
1)
b0 .
b0 /
1!
#2675009
0!
#2680009
b0 %
0&
b1 '
0)
b1 /
1!
#2685009
0!
#2690009
1#
b10101111 %
1&
1!
#2695009
0!
#2700009
b0 %
0&
b10 '
b1 (
b10 /
0)
b1 .
b1000100 -
1!
#2705009
0!
#2710009
0#
b10 (
1)
b10 .
b10101111 -
1!
#2715009
0!
#2720009
1#
b1 %
1&
1!
#2725009
0!
#2730009
0#
b1010010 %
b11 '
0)
b11 /
1!
#2735009
0!
#2740009
1#
b0 %
0&
b100 '
b100 /
1!
#2745009
0!
#2750009
0#
0$
b11 (
b11 .
b1 -
1!
#2755009
0!
#2760009
1$
b0 '
b0 (
1)
b0 /
b0 -
b0 .
1!
#2765009
0!
#2770009
1!
#2775009
0!
#2780009
1#
b10100 %
1&
1!
#2785009
0!
#2790009
b110100 %
b1 '
0)
b1 /
1!
#2795009
0!
#2800009
0#
b0 %
0&
b10 '
b1 (
b10 /
0)
b1 .
b10100 -
1!
#2805009
0!
#2810009
1!
#2815009
0!
#2820009
b1011010 %
1&
1!
#2825009
0!
#2830009
b10101010 %
b11 '
b11 /
1!
#2835009
0!
#2840009
b1111111 %
b100 '
b100 /
1!
#2845009
0!
#2850009
1#
b0 %
0&
b101 '
b101 /
1!
#2855009
0!
#2860009
b10 (
b10 .
b110100 -
1!
#2865009
0!
#2870009
b1110100 %
1&
b11 (
b11 .
b1011010 -
1!
#2875009
0!
#2880009
b0 %
0&
b110 '
b100 (
b110 /
b100 .
b10101010 -
1!
#2885009
0!
#2890009
0#
b10110011 %
1&
b101 (
b101 .
b1111111 -
1!
#2895009
0!
#2900009
b10101001 %
b111 '
b111 /
1!
#2905009
0!
#2910009
b1011011 %
b1000 '
b1000 /
1!
#2915009
0!
#2920009
1#
b0 %
0&
b1001 '
b1001 /
1!
#2925009
0!
#2930009
0#
b11011111 %
1&
b110 (
b110 .
b1110100 -
1!
#2935009
0!
#2940009
1#
b0 %
0&
b1010 '
b1010 /
1!
#2945009
0!
#2950009
0#
1&
b111 (
b111 .
b10110011 -
1!
#2955009
0!
#2960009
0&
b1011 '
b1011 /
1!
#2965009
0!
#2970009
1#
1!
#2975009
0!
#2980009
0#
b1000 (
b1000 .
b10101001 -
1!
#2985009
0!
#2990009
1#
1!
#2995009
0!
#3000009
0#
b1001 (
b1001 .
b1011011 -
1!
#3005009
0!
#3010009
1!
#3015009
0!
#3020009
1#
1!
#3025009
0!
#3030009
0#
b11001111 %
1&
b1010 (
b1010 .
b11011111 -
1!
#3035009
0!
#3040009
1#
b11011100 %
b1100 '
b1100 /
1!
#3045009
0!
#3050009
b0 %
0&
b1011 (
b1101 '
b1011 .
b0 -
b1101 /
1!
#3055009
0!
#3060009
0#
b1100 (
b1100 .
b11001111 -
1!
#3065009
0!
#3070009
1!
#3075009
0!
#3080009
b10101011 %
1&
1!
#3085009
0!
#3090009
1#
b0 %
0&
b1110 '
b1110 /
1!
#3095009
0!
#3100009
b1101 (
b1101 .
b11011100 -
1!
#3105009
0!
#3110009
0#
b1110 (
1)
b1110 .
b10101011 -
1!
#3115009
0!
#3120009
b1100011 %
1&
1!
#3125009
0!
#3130009
1#
b1001011 %
b1111 '
0)
b1111 /
1!
#3135009
0!
#3140009
0#
b110110 %
b0 '
b1111 (
b10000 /
0)
b1111 .
b1100011 -
1!
#3145009
0!
#3150009
b11101101 %
b1 '
b10001 /
1!
#3155009
0!
#3160009
b11101001 %
b10 '
b10010 /
1!
#3165009
0!
#3170009
b10100010 %
b11 '
b10011 /
1!
#3175009
0!
#3180009
b0 %
0&
b100 '
b10100 /
1!
#3185009
0!
#3190009
1!
#3195009
0!
#3200009
1!
#3205009
0!
#3210009
1#
b10001101 %
1&
1!
#3215009
0!
#3220009
0#
b0 %
0&
b101 '
b0 (
b10101 /
b10000 .
b1001011 -
1!
#3225009
0!
#3230009
1#
b10001011 %
1&
1!
#3235009
0!
#3240009
b0 %
0&
b110 '
b1 (
b10110 /
b10001 .
b110110 -
1!
#3245009
0!
#3250009
b1101101 %
1&
b10 (
b10010 .
b11101101 -
1!
#3255009
0!
#3260009
0#
b11010100 %
b111 '
b11 (
b10111 /
b10011 .
b11101001 -
1!
#3265009
0!
#3270009
1#
b0 %
0&
b1000 '
b11000 /
1!
#3275009
0!
#3280009
b100 (
b10100 .
b10100010 -
1!
#3285009
0!
#3290009
b101 (
b10101 .
b10001101 -
1!
#3295009
0!
#3300009
b11010110 %
1&
b110 (
b10110 .
b10001011 -
1!
#3305009
0!
#3310009
0#
b0 %
0&
b111 (
b1001 '
b10111 .
b1101101 -
b11001 /
1!
#3315009
0!
#3320009
1#
b11111000 %
1&
1!
#3325009
0!
#3330009
0#
b11001111 %
b1000 (
b1010 '
b11000 .
b11010100 -
b11010 /
1!
#3335009
0!
#3340009
b0 %
0&
b1011 '
b11011 /
1!
#3345009
0!
#3350009
1!
#3355009
0!
#3360009
1#
1!
#3365009
0!
#3370009
b1001 (
b11001 .
b11010110 -
1!
#3375009
0!
#3380009
b10101100 %
1&
b1010 (
b11010 .
b11111000 -
1!
#3385009
0!
#3390009
0#
b11010111 %
b1011 (
b1100 '
b11011 .
b11001111 -
b11100 /
1!
#3395009
0!
#3400009
1#
b11010 %
b1101 '
b11101 /
1!
#3405009
0!
#3410009
0#
b10100 %
b1100 (
b1110 '
b11100 .
b10101100 -
b11110 /
1!
#3415009
0!
#3420009
1#
b0 %
0&
b1111 '
b11111 /
1!
#3425009
0!
#3430009
b111010 %
1&
b1101 (
b11101 .
b11010111 -
1!
#3435009
0!
#3440009
0#
b10111100 %
b0 '
b1110 (
b0 /
b11110 .
b11010 -
1!
#3445009
0!
#3450009
b0 %
0&
b1 '
b1 /
1!
#3455009
0!
#3460009
1!
#3465009
0!
#3470009
1#
b11000000 %
1&
1!
#3475009
0!
#3480009
b0 %
0&
b10 '
b1111 (
b10 /
b11111 .
b10100 -
1!
#3485009
0!
#3490009
b0 (
b0 .
b111010 -
1!
#3495009
0!
#3500009
0#
b1 (
b1 .
b10111100 -
1!
#3505009
0!
#3510009
1!
#3515009
0!
#3520009
1#
b10101110 %
1&
1!
#3525009
0!
#3530009
0#
0&
0$
b10 (
b11 '
b10 .
b11000000 -
b11 /
1!
#3535009
0!
#3540009
1#
b10111001 %
1&
1$
b0 '
b0 (
1)
b0 /
b0 -
b0 .
1!
#3545009
0!
#3550009
0#
b0 %
0&
b1 '
0)
b1 /
1!
#3555009
0!
#3560009
1!
#3565009
0!
#3570009
1!
#3575009
0!
#3580009
b10001001 %
1&
1!
#3585009
0!
#3590009
b10001110 %
b10 '
b10 /
1!
#3595009
0!
#3600009
1#
b11000010 %
b11 '
b11 /
1!
#3605009
0!
